{"by_version": {"19.3b0": 24473, "18.9b0": 6742, "19.10b0": 27074, "18.5b0": 77, "18.6b4": 749, "18.5b1": 91, "18.3a1": 46, "18.3a2": 46, "18.4a4": 50, "18.3a4": 49, "18.4a2": 49, "18.6b1": 146, "18.4a0": 50, "18.6b0": 54, "18.6b2": 148, "18.4a1": 49, "18.6b3": 50, "18.3a0": 46, "18.4a3": 50, "18.3a3": 49}, "by_file_type": {"bdist_wheel": 57990, "sdist": 2098}, "by_installer": {"setuptools": {"41.2.0": 9, "41.6.0.post20191030": 4, "40.6.2": 1, "41.6.0": 35, "40.4.3": 2, "41.0.1": 44, "40.8.0": 16, "41.4.0": 3}, "requests": {"2.18.4": 2, "2.22.0": 221, "2.21.0": 5, "2.19.1": 22}, "Artifactory": {"6.14.1": 2, "6.11.3": 5, "6.13.1": 2, "6.12.2": 61, "6.10.1": 1, "6.9.1": 1, "6.6.5": 2, "6.5.15": 1, "6.14.0": 570, "6.11.1": 1}, "devpi": {"4.8.0": 1, "4.1.0": 1, "4.0.0": 1, "4.9.0": 2, "4.2.1": 2, "5.2.0": 1, "4.5.0": 1}, "pip": {"20.0.dev0": 1, "19.1.1": 2750, "19.0.1": 43, "19.1": 171, "19.0": 1, "7.0.3": 1, "6.1.1": 1, "8.1.2": 1, "9.0.1": 1690, "9.0.3": 983, "9.0.2": 73, "8.1.1": 31, "19.0.3": 2940, "19.3": 1317, "18.0": 234, "19.3.1": 32694, "18.1": 7167, "19.2.2": 1712, "19.0.2": 92, "19.2.1": 416, "19.2": 4, "19.2.3": 4493, "10.0.1": 786, "10.0.0": 1}, "Nexus": {"3.15.2-01": 38, "3.16.0-01": 1, "3.19.1-01": 26, "3.19.0-01": 1, "3.18.1-01": 8, "3.3.1-01": 2, "3.16.2-01": 3, "3.4.0-02": 1, "3.2.1-01": 1, "3.17.0-01": 9, "3.15.1-01": 2, "3.7.1-02": 1, "3.16.1-02": 9, "3.12.0-01": 1, "3.14.0-04": 20, "3.13.0-01": 2, "3.18.0-01": 6}, "pex": {"1.6.11": 3, "1.4.3": 1, "1.6.8": 33, "1.6.12": 331}, "null": {"null": 28}, "Homebrew": {"2.1.16": 2}, "Browser": {"null": 38}, "Bazel": {"0.25.2": 2, "0.23.1": 12, "1.2.0": 5, "0.29.1": 1}, "bandersnatch": {"3.6.0": 840, "1.11": 40}}, "by_implementation": {"CPython": {"3.7.5rc1": 51, "3.6.5": 1076, "3.6.4": 437, "2.7.10": 2, "3.8.0b4": 2, "3.6.9": 7908, "3.7.5": 16354, "2.7.17rc1": 1, "3.6.3": 488, "3.8.0+": 111, "2.7.12": 3, "3.7.2+": 1, "3.7.4": 6418, "3.6.6": 550, "3.7.3": 5753, "3.7.0b3": 10, "3.7.5+": 28, "3.7.0": 496, "3.6.2": 152, "3.5.2": 13, "3.7.1rc1": 2, "3.8.0": 2782, "3.6.1": 130, "3.8.0b3": 34, "2.7.5": 1, "3.6.0": 77, "3.8.0rc1": 5, "3.6.8": 7841, "3.8.0b1": 10, "2.7.15": 1, "3.7.2": 2060, "3.7.1": 2077, "3.6.2+": 1, "3.7.0b4": 1, "3.6.7": 2713}, "PyPy": {"7.2.0": 10, "7.1.1.beta.0": 3}, "null": {"null": 2486}}, "by_system": {"Linux": 54018, "Darwin": 2182, "OpenBSD": 1, "null": 2486, "FreeBSD": 3, "Windows": 1398}, "by_distro": {"Ubuntu": {"16.04": 8953, "19.04": 170, "18.04": 10486, "17.10": 5, "14.04": 1593, "19.10": 52, "18.10": 44}, "Alpine Linux": {"3.10.2": 306, "3.9.3": 83, "3.10.1": 80, "3.6.5": 13, "3.10.0": 241, "3.9.2": 111, "3.8.2": 68, "3.10.3": 1803, "3.8.1": 63, "3.9.0": 34, "3.7.0": 117, "3.11_alpha20190809": 1, "3.7.1": 84, "3.7.3": 19, "3.9.4": 570, "3.4.6": 16, "3.10_beta20190508": 1, "3.6.3": 6, "3.8.4": 94, "3.8.0": 3, "3.11_alpha20191114": 2}, "macOS": {"10.14.4": 118, "10.14.3": 9, "10.15": 44, "10.14.2": 6, "10.15.2": 2, "10.14": 6, "10.15.1": 506, "10.12.5": 2, "10.13.6": 315, "10.11.6": 3, "10.13.1": 1, "10.13.4": 4, "10.13.3": 110, "10.12.6": 17, "10.14.5": 48, "10.13.5": 1, "10.14.6": 987, "10.14.1": 2}, "Red Hat Enterprise Linux Server": {"7.5": 5, "5.3": 1, "7.6": 16, "6.10": 1, "7.7": 40, "7.4": 4}, "KDE neon": {"18.04": 5}, "Raspbian GNU/Linux": {"9": 1, "10": 5}, "Fedora": {"30": 257, "28": 2, "27": 1, "29": 55, "20": 2, "31": 75}, "CentOS Linux": {"7.6.1810": 1, "7": 2007, "8": 6}, "Debian GNU/Linux": {"rodete": 3, "stable-updates": 5, "10": 14011, "null": 4, "8": 685, "unstable": 4, "9": 10686, "testing": 5}, "openSUSE Leap": {"42.3": 1, "42.2": 1}, "SLED": {"15": 1}, "Amazon Linux AMI": {"2017.09": 9, "2018.03": 359, "2017.03": 24}, "CentOS": {"5.11": 1, "6.6": 84, "6.8": 1, "6.10": 15}, "Freedesktop.org": {"19.08.3": 1}, "Arch Linux": {"rolling": 30, "v19.07.9": 1, "2019.1.20": 1, "null": 100}, "Manjaro Linux": {"null": 1, "18.1.2": 4, "18.1.3": 46}, "Antergos Linux": {"null": 2}, "Red Hat Enterprise Linux Client": {"7.7": 1}, "OS X": {"10.12.6": 2, "10.14.6": 1}, "Kali GNU/Linux": {"2019.2": 1, "2019.3": 1, "2019.4": 2}, "Linux Mint": {"19.1": 8, "18.3": 3, "19": 1, "19.2": 13}, "Red Hat Enterprise Linux": {"8.1": 34, "8.0": 1}, "Oracle Linux Server": {"7.7": 14, "7.6": 1}, "SLES": {"11.4": 1}, "Deepin": {"15.11": 2, "15.10.1": 1}, "Zorin": {"12": 1}, "LinuxMint": {"18.3": 1}, "Pengwin": {"10": 2}, "null": {"null": 3891}, "Pop!_OS": {"19.10": 8, "18.04": 1, "19.04": 1}, "Poky (Yocto Project Reference Distro)": {"2.7.1": 9}, "Parrot GNU/Linux": {"4.7": 2}, "ArchLabs": {"2019.10.29": 1}, "void": {"rolling": 1}, "Amazon Linux": {"2": 306}, "VMware Photon OS": {"2.0": 1}, "Gentoo": {"2.6": 3}, "Slackware": {"14.2": 1}, "openSUSE Tumbleweed": {"20191119": 2}, "RedHatEnterpriseWorkstation": {"6.7": 1}, "RedHatEnterpriseServer": {"6.6": 1}}, "by_country": {"FR": 1299, "DO": 7, "ID": 22, "VE": 3, "MK": 7, "FI": 141, "NL": 601, "EG": 6, "SN": 1, "AL": 1, "MX": 32, "RO": 49, "BD": 2, "PT": 35, "IE": 3922, "DE": 2876, "EU": 329, "PL": 323, "MU": 2, "HK": 100, "PE": 3, "MT": 1, "GT": 6, "KR": 106, "CA": 772, "GB": 1133, "BE": 113, "AU": 423, "RU": 447, "ZA": 18, "BA": 5, "LU": 4, "NZ": 68, "IN": 254, "SK": 16, "CU": 4, "BG": 23, "SA": 7, "SI": 7, "TW": 12, "MY": 7, "UZ": 2, "PK": 8, "RW": 1, "UY": 1, "US": 43392, "SE": 245, "MD": 3, "ME": 3, "CN": 119, "PH": 20, "TH": 16, "KE": 17, "AE": 2, "GR": 7, "ET": 2, "BR": 262, "CZ": 106, "TR": 21, "IT": 63, "TL": 1, "IS": 5, "HU": 9, "IL": 9, "AR": 17, "RS": 4, "BY": 62, "CL": 8, "IQ": 1, "null": 566, "SG": 209, "AT": 192, "CO": 16, "CH": 163, "PR": 5, "KZ": 6, "BT": 1, "PY": 1, "SO": 2, "MA": 4, "CD": 2, "JP": 367, "UA": 229, "BO": 3, "LT": 19, "NO": 70, "CY": 1, "AP": 142, "ES": 193, "DK": 247, "VN": 33, "HR": 8, "NP": 3, "EE": 4, "LV": 5, "MN": 1, "TN": 3}, "cache_metadata": {"project": "black", "date": "20191122", "updated": 1578052305.69832, "version": "0.2.1", "data_ts": 1574467199}}