{"by_version": {"18.9b0": 2922, "18.6b2": 28, "18.6b1": 3, "18.6b4": 148, "18.5b1": 9, "18.6b3": 1, "19.3b0": 10976}, "by_file_type": {"sdist": 281, "bdist_wheel": 13806}, "by_installer": {"Nexus": {"3.15.2-01": 25, "3.16.2-01": 3, "3.17.0-01": 3, "3.18.1-01": 2, "3.18.0-01": 3, "3.14.0-04": 1, "3.16.0-01": 1}, "pip": {"10.0.1": 111, "8.1.2": 4, "9.0.3": 117, "19.0.3": 1364, "8.1.1": 30, "9.0.1": 333, "19.1.1": 466, "19.2.2": 320, "19.1": 52, "19.0.1": 249, "10.0.0": 3, "18.0": 14, "7.1.2": 1, "9.0.2": 46, "19.2.3": 8535, "18.1": 1368, "19.2.1": 417, "19.0.2": 22, "19.3.dev0": 1, "1.5.6": 2, "19.2": 1}, "pex": {"1.5.3": 1, "1.6.11": 7}, "setuptools": {"39.0.1": 1, "40.8.0": 3, "41.2.0": 6}, "Bazel": {"0.23.1": 12, "0.25.2": 1}, "requests": {"2.19.1": 16, "2.21.0": 2, "2.22.0": 23}, "Browser": {"null": 2}, "bandersnatch": {"2.2.1": 4}, "Artifactory": {"6.12.2": 32, "6.11.3": 482}, "devpi": {"4.8.0": 1}}, "by_implementation": {"CPython": {"3.8.0b4+": 48, "3.6.2": 253, "3.7.1": 729, "3.6.5": 110, "3.7.4+": 34, "3.4.2": 2, "3.7.2": 511, "3.5.2": 23, "3.6.0": 10, "3.6.6": 427, "3.6.3": 142, "3.7.4": 4614, "3.8.0b3": 28, "3.7.3": 1007, "3.7.0": 82, "3.6.8": 1885, "3.6.4": 119, "2.7.12": 5, "2.7.5": 2, "3.6.9+": 7, "2.7.13": 1, "2.7.15+": 1, "3.6.9": 2606, "3.7.0b3": 17, "3.8.0b1": 1, "3.6.7": 718, "3.6.1": 24, "3.8.0b4": 38, "3.6.2+": 1}, "null": {"null": 631}, "PyPy": {"7.1.1.beta.0": 11}}, "by_system": {"Linux": 12440, "Darwin": 591, "FreeBSD": 1, "Windows": 424, "null": 631}, "by_distro": {"Debian GNU/Linux": {"10": 2285, "9": 3277, "testing": 3, "8": 358, "unstable": 2, "null": 4}, "Fedora": {"29": 50, "28": 50, "30": 26, "18": 1}, "Pop!_OS": {"18.10": 1, "19.04": 4}, "Alpine Linux": {"3.10.1": 25, "3.9.4": 84, "3.8.1": 5, "3.9.2": 20, "3.8.4": 4, "3.9.3": 5, "3.11_alpha20190707": 4, "3.9.0": 3, "3.7.0": 3, "3.7.3": 11, "3.8.2": 2, "3.10.0": 20, "3.10.2": 423, "3.7.1": 10, "3.4.6": 1, "3.11_alpha20190925": 3}, "macOS": {"10.14.3": 5, "10.13.3": 31, "10.14.6": 319, "10.14.1": 3, "10.14": 5, "10.14.5": 20, "10.11.6": 1, "10.10.5": 1, "10.12.1": 1, "10.15": 6, "10.14.4": 27, "10.13.6": 164, "10.12.6": 5, "10.14.2": 2, "10.13.4": 1}, "Ubuntu": {"17.10": 2, "19.10": 7, "14.04": 725, "18.04": 1910, "19.04": 72, "16.04": 2009, "18.10": 32}, "openSUSE Leap": {"15.1": 1}, "Amazon Linux AMI": {"2017.09": 4, "2018.03": 161, "2017.03": 11}, "CentOS": {"6.10": 162, "5.11": 12}, "LinuxMint": {"18.3": 1}, "Raspbian GNU/Linux": {"10": 4}, "void": {"rolling": 1}, "Manjaro Linux": {"18.1.0": 16, "18.0.4": 1}, "Arch Linux": {"rolling": 12, "null": 21}, "Oracle Linux Server": {"7.6": 1}, "Linux Mint": {"19.2": 5, "18.3": 4, "19": 1, "19.1": 1}, "Kali GNU/Linux": {"2019.4": 2}, "Feren OS": {"18.04": 1}, "Funtoo GNU/Linux": {"intel64-skylake-2019-09-05": 1}, "Gentoo": {"2.6": 4}, "NixOS": {"19.03.173522.021d733ea3f": 1, "19.03.173506.2dfae8e22fd": 1}, "elementary OS": {"5.0": 3, "0.4.1": 1}, "CentOS Linux": {"7.7.1908": 2, "7": 542, "7.6.1810": 1}, "Amazon Linux": {"2": 7}, "KDE neon": {"18.04": 2}, "Clear Linux OS": {"31070": 2}, "openSUSE Tumbleweed": {"20190925": 1}, "Deepin": {"15.11": 1}, "debian": {"8.6": 1}, "Antergos Linux": {"rolling": 1}, "null": {"null": 1061}, "Red Hat Enterprise Linux": {"8.0": 1}}, "by_country": {"SE": 93, "IT": 13, "AU": 69, "SA": 2, "CR": 3, "ZA": 6, "SK": 3, "NO": 7, "RS": 1, "DE": 398, "CH": 28, "TW": 9, "GH": 2, "MY": 2, "PE": 2, "AE": 1, "IL": 15, "US": 11088, "GB": 192, "NZ": 16, "CA": 119, "CO": 14, "BE": 15, "BR": 50, "KR": 38, "MX": 13, "RO": 3, "EG": 2, "CU": 1, "CL": 2, "IS": 1, "NP": 2, "ME": 1, "RU": 78, "JP": 110, "KE": 4, "HR": 1, "HN": 1, "DZ": 1, "EU": 282, "EE": 3, "BG": 5, "CZ": 32, "ID": 5, "AT": 10, "LT": 6, "CY": 1, "SV": 1, "SI": 1, "PL": 65, "AR": 30, "HK": 57, "TR": 7, "CN": 32, "NG": 3, "JO": 1, "LK": 2, "PH": 3, "YE": 2, "BF": 1, "IE": 406, "FI": 37, "ES": 18, "NL": 85, "GR": 3, "IR": 3, "UY": 1, "FR": 77, "VN": 12, "HU": 2, "BD": 2, "null": 202, "IN": 122, "AP": 32, "UA": 11, "SG": 98, "LV": 1, "LB": 1, "BY": 4, "DK": 5, "TH": 8, "PR": 2}, "cache_metadata": {"project": "black", "date": "20190928", "updated": 1578051068.903696, "version": "0.2.1", "data_ts": 1569715199}}