{"by_version": {"0.7.1": 35, "0.16.3": 107, "0.11.0": 10, "0.2.9": 6, "0.7.0": 7, "0.17.0": 109, "0.20.2": 439, "0.2.0": 6, "0.1.6": 5, "0.3.0": 6, "0.26.0": 4059, "0.27.0": 4495, "0.6.2": 7, "0.13.1": 6, "0.12.0": 6, "0.15.1": 6, "0.1.7": 6, "0.8.2": 6, "0.8.0": 6, "0.21.0": 1914, "0.13.2": 346, "0.16.1": 17, "0.2.4": 6, "0.23.0": 142, "0.9.0": 6, "0.2.1": 6, "0.6.1": 6, "0.8.1": 6, "0.4.0": 6, "0.10.0": 7, "0.1.4": 5, "0.22.0": 645, "0.15.0": 6, "0.3.1": 6, "0.1.5": 5, "0.11.1": 7, "0.2.3": 6, "0.6.0": 6, "0.2.5": 6, "0.25.0": 840, "0.19.0": 67, "0.2.8": 6, "0.12.1": 6, "0.6.3": 6, "0.18.0": 65, "0.28.0": 9076, "0.24.0": 637, "0.20.1": 242, "0.16.0": 66, "0.2.7": 6, "0.12.2": 6, "0.13.0": 6, "0.2.2": 6, "0.2.6": 6, "0.1.9": 6, "0.14.0": 456, "0.20.0": 523, "0.16.2": 35, "0.15.2": 10, "0.1.8": 6, "0.5.0": 6}, "by_file_type": {"sdist": 600, "bdist_wheel": 23964}, "by_installer": {"requests": {"2.22.0": 125, "2.21.0": 1}, "setuptools": {"39.0.1": 4, "40.8.0": 1, "41.2.0": 6, "41.0.1": 6, "41.4.0": 20, "40.6.3": 2}, "Artifactory": {"6.12.0": 4, "6.13.0": 1, "6.5.9": 1, "6.12.2": 2, "6.3.3": 1}, "Nexus": {"3.19.1-01": 1, "3.14.0-04": 1, "3.18.0-01": 2, "3.17.0-01": 6, "3.15.1-01": 1, "3.16.2-01": 3, "3.11.0-01": 2, "3.16.1-02": 9, "3.18.1-01": 4, "3.15.2-01": 24}, "pip": {"8.1.1": 263, "9.0.2": 6, "9.0.3": 525, "19.2": 8, "19.1": 20, "8.1.2": 5, "6.1.1": 1, "18.0": 196, "10.0.0": 4, "10.0.1": 2818, "1.5.4": 1, "1.5.6": 5, "19.1.1": 617, "19.0.3": 1169, "18.1": 1522, "19.2.2": 100, "19.0.1": 17, "9.0.1": 1778, "19.2.3": 13082, "19.2.1": 1772, "19.0.2": 17, "7.1.2": 4, "6.0.6": 1}, "devpi": {"5.1.0": 2, "4.7.1": 1}, "Bazel": {"development version": 52}, "bandersnatch": {"3.6.0": 141, "3.1.3": 180}, "null": {"null": 21}, "OS": {"null": 2}, "Browser": {"null": 7}}, "by_implementation": {"CPython": {"3.6.2": 1376, "3.7.3": 1157, "3.5.7": 129, "3.6.5": 290, "2.7.14": 58, "2.7.16+": 39, "3.7.5rc1": 14, "3.4.8": 7, "3.7.5rc1+": 3, "3.7.4": 2615, "2.7.15+": 674, "3.4.10": 31, "2.7.9": 24, "3.6.1": 22, "3.7.2": 405, "3.5.6": 149, "3.8.0a1": 1, "3.6.8": 2422, "2.7.16": 986, "3.7.1": 479, "3.4.3": 1, "3.5.4": 29, "3.5.1+": 200, "2.7.3": 3, "3.5.2": 200, "2.7.15rc1": 31, "3.6.7": 690, "2.7.11": 1, "3.5.3": 369, "3.6.9": 1896, "3.5.5": 7, "2.7.13": 3389, "3.7.0": 3471, "3.5.8rc1": 2, "3.4.0": 1, "3.6.3": 240, "2.7.15": 99, "3.8.0b2": 1, "2.7.5": 67, "3.6.6": 484, "2.7.10": 14, "2.7.12": 919, "3.8.0b4": 11, "3.5.0": 21, "3.8.0rc1+": 8, "3.6.9+": 1, "2.7.6": 84, "3.6.0": 610, "3.6.4": 178, "3.4.2": 4, "3.4.7": 2, "3.8.0a3": 3}, "null": {"null": 633}, "PyPy": {"5.8.0": 4, "7.1.1": 5, "5.10.1": 5}}, "by_system": {"null": 633, "Windows": 2094, "Darwin": 838, "Linux": 20999}, "by_distro": {"macOS": {"10.15": 90, "10.14.5": 41, "10.13.6": 243, "10.14.1": 4, "10.14": 1, "10.13": 1, "10.14.4": 185, "10.14.3": 1, "10.14.2": 4, "10.11.6": 2, "10.13.1": 1, "10.13.3": 65, "10.10.5": 1, "10.15.1": 2, "10.13.4": 2, "10.12.6": 2, "10.14.6": 192}, "Amazon Linux AMI": {"2017.09": 39, "2016.09": 2, "2016.03": 1, "2018.03": 643}, "Gentoo": {"2.6": 3}, "RedHatEnterpriseServer": {"6.7": 2, "6.2": 1965, "6.10": 1}, "Kali GNU/Linux": {"2019.3": 1, "2019.2": 1, "2019.4": 4}, "Red Hat Enterprise Linux Server": {"7.3": 2, "7.5": 4, "7.7": 14, "7.0": 729, "7.6": 123, "7.4": 4}, "Antergos Linux": {"null": 1, "rolling": 1}, "Ubuntu": {"16.04": 4045, "19.10": 6, "18.04": 2343, "14.04": 284, "19.04": 79, "17.10": 2, "18.10": 70}, "Alpine Linux": {"3.10.1": 57, "3.6.3": 1, "3.9.0": 4, "3.7.0": 19, "3.8.4": 36, "3.10.2": 213, "3.7.3": 26, "3.9.4": 88, "3.11_alpha20190925": 17, "3.7.1": 10, "3.8.2": 19, "3.9.2": 29, "3.10.0": 2}, "Oracle Linux Server": {"7.7": 7, "7.5": 1, "7.6": 2}, "debian": {"8.2": 3, "jessie/sid": 6, "stretch/sid": 9}, "SLES": {"12.4": 3, "12.2": 4, "12.3": 9, "12.1": 3}, "Deepin": {"15.11": 2}, "CentOS": {"6.8": 2, "6.4": 1, "6.10": 32}, "MongoDB database server": {"20190929193321": 1}, "Debian GNU/Linux": {"stable-updates": 1, "10": 2289, "testing": 1, "9": 6481, "null": 34, "8": 177}, "Manjaro Linux": {"18.0.4": 1, "18.1.0": 12}, "Zorin OS": {"15": 1}, "Arch Linux": {"rolling": 13, "2019.1.20": 2, "null": 41}, "Raspbian GNU/Linux": {"10": 3}, "Pop!_OS": {"19.04": 1, "18.04": 1}, "elementary OS": {"5.0": 1}, "CentOS Linux": {"7.6.1810": 2, "7.5.1804": 1, "7": 625, "7.4.1708": 1}, "null": {"null": 2741}, "Red Hat Enterprise Linux": {"8.0": 55}, "Scientific Linux": {"7.7": 2}, "Linux Mint": {"19.1": 7, "19": 5, "19.2": 15, "18.3": 6}, "Fedora": {"30": 11, "28": 68, "29": 4, "27": 2}, "Alibaba Group Enterprise Linux Server": {"7.2": 1}, "openSUSE Tumbleweed": {"20191007": 1}, "SUSE LINUX": {"11": 3}, "Amazon Linux": {"2": 138}, "LinuxMint": {"18.2": 1}, "Red Hat Enterprise Linux Workstation": {"7.6": 1}, "OS X": {"10.14.6": 1}, "KDE neon Plasma LTS": {"18.04": 2}}, "by_country": {"HK": 40, "KR": 186, "NO": 9, "TN": 1, "BO": 2, "PH": 5, "CO": 1, "SN": 1, "US": 20121, "AU": 56, "DO": 1, "SK": 5, "KZ": 2, "AP": 63, "SE": 46, "HU": 10, "TR": 8, "TH": 6, "KY": 3, "BR": 44, "UA": 19, "SG": 29, "IL": 9, "RO": 5, "LU": 3, "SA": 2, "IN": 98, "FI": 27, "ID": 43, "AE": 3, "CR": 5, "AZ": 1, "EE": 1, "GE": 1, "GT": 1, "SI": 1, "DE": 322, "IR": 6, "PT": 24, "NG": 3, "NP": 2, "CM": 2, "MA": 2, "KG": 1, "KE": 1, "IT": 48, "CZ": 21, "CH": 68, "GB": 262, "NZ": 3, "MD": 2, "AR": 13, "LT": 1, "FR": 391, "ES": 22, "PE": 4, "QA": 1, "BY": 10, "GR": 2, "BG": 2, "TZ": 1, "HR": 2, "MX": 11, "UY": 1, "AT": 26, "RS": 14, "VN": 23, "null": 765, "JP": 462, "TW": 25, "DK": 13, "GH": 1, "CL": 7, "LB": 2, "EG": 3, "CU": 2, "CN": 209, "RU": 94, "EU": 101, "BE": 14, "MY": 3, "ZA": 1, "NL": 127, "IE": 476, "PL": 33, "CA": 75, "PK": 2}, "cache_metadata": {"project": "yapf", "date": "20191009", "updated": 1578051294.5262146, "version": "0.2.1", "data_ts": 1570665599}}