{"by_version": {"0.10.0": 5, "0.1.4": 4, "0.22.0": 881, "0.11.1": 6, "0.3.1": 4, "0.1.5": 4, "0.15.0": 4, "0.23.0": 122, "0.6.1": 4, "0.8.1": 4, "0.2.1": 4, "0.9.0": 6, "0.4.0": 4, "0.28.0": 7937, "0.24.0": 695, "0.18.0": 103, "0.16.0": 139, "0.20.1": 171, "0.2.2": 4, "0.12.2": 4, "0.2.6": 4, "0.13.0": 4, "0.1.9": 4, "0.2.7": 4, "0.21.0": 1238, "0.13.2": 205, "0.16.1": 20, "0.2.4": 4, "0.27.0": 4144, "0.26.0": 2242, "0.13.1": 4, "0.12.0": 4, "0.8.0": 4, "0.6.2": 6, "0.8.2": 4, "0.1.7": 4, "0.15.1": 5, "0.7.1": 33, "0.16.3": 115, "0.2.9": 4, "0.7.0": 4, "0.11.0": 5, "0.20.2": 306, "0.17.0": 65, "0.1.6": 4, "0.3.0": 4, "0.2.0": 4, "0.6.0": 4, "0.2.5": 4, "0.2.3": 4, "0.14.0": 450, "0.20.0": 971, "0.16.2": 25, "0.15.2": 9, "0.5.0": 4, "0.1.8": 4, "0.25.0": 913, "0.19.0": 96, "0.12.1": 4, "0.2.8": 4, "0.6.3": 4}, "by_file_type": {"bdist_wheel": 20547, "sdist": 498}, "by_installer": {"pip": {"18.0": 315, "10.0.0": 6, "19.1.1": 637, "9.0.2": 13, "19.0.3": 1134, "18.1": 1264, "2019.12": 1, "7.1.0": 2, "19.0.1": 164, "19.2.2": 253, "19.2.3": 12137, "9.0.1": 1430, "19.2.1": 1416, "19.0.2": 60, "8.1.2": 3, "19.1": 15, "8.1.1": 256, "9.0.3": 561, "19.2": 6, "1.5.6": 11, "10.0.1": 918, "1.5.4": 3}, "Artifactory": {"6.10.1": 1, "6.11.1": 1, "6.11.3": 2, "6.12.2": 2}, "Nexus": {"3.16.2-01": 6, "3.17.0-01": 6, "3.14.0-04": 1, "3.15.1-01": 1, "3.18.1-01": 7, "3.15.2-01": 25, "3.16.1-02": 3, "3.18.0-01": 4}, "setuptools": {"41.2.0": 27, "41.0.1": 22, "32.1.2": 1, "40.6.3": 2}, "requests": {"2.22.0": 101, "2.18.4": 1}, "OS": {"null": 1}, "null": {"null": 1}, "bandersnatch": {"3.5.0": 12, "3.1.3": 180, "3.2.0": 4}, "Browser": {"null": 4}, "Bazel": {"development version": 25}}, "by_implementation": {"CPython": {"3.6.3": 261, "2.7.15": 150, "3.7.0": 1521, "2.7.13": 3674, "3.8.0b4+": 15, "3.4.1": 1, "3.4.6": 2, "3.5.8rc1": 11, "3.6.0": 236, "3.6.4": 176, "2.7.6": 99, "3.4.2": 9, "3.6.2": 1194, "3.7.3": 1205, "3.5.3": 557, "3.6.9": 975, "3.5.5": 5, "3.7.4": 2139, "2.7.15+": 604, "2.7.9": 17, "3.4.10": 36, "3.6.1": 31, "2.7.3": 2, "3.5.4": 58, "3.5.1+": 139, "3.6.8": 2064, "2.7.16": 531, "3.7.4+": 31, "3.7.1": 459, "3.4.3": 3, "3.5.2": 450, "3.6.7": 798, "2.7.15rc1": 31, "2.7.11": 2, "2.7.5": 58, "3.6.6": 611, "2.7.12": 756, "2.7.10": 28, "3.8.0b4": 41, "3.5.0": 22, "3.6.9+": 15, "3.7.0b1": 1, "3.7.2": 766, "3.5.6": 145, "3.4.9": 4, "3.5.1": 2, "2.7.14": 116, "3.5.7": 123, "3.6.5": 355, "2.7.16+": 23, "3.4.8": 4}, "PyPy": {"7.1.1.beta.0": 10, "5.8.0": 15, "7.3.0.alpha.0": 10, "5.10.1": 14}, "null": {"null": 440}}, "by_system": {"Darwin": 635, "CYGWIN_NT-10.0": 1, "CYGWIN_NT-10.0-17763": 1, "FreeBSD": 1, "null": 440, "Windows": 2094, "OpenBSD": 1, "Linux": 17872}, "by_distro": {"Debian GNU/Linux": {"8": 356, "unstable": 3, "9": 5809, "null": 26, "oldstable-updates": 2, "10": 1818, "7": 2, "testing": 1}, "macOS": {"10.14.6": 213, "10.12.6": 12, "10.14.4": 130, "10.14.3": 4, "10.14.2": 4, "10.11.6": 2, "10.14": 10, "10.13.6": 183, "10.12.5": 1, "10.14.5": 40, "10.15": 11, "10.13.3": 21, "10.10.5": 1, "10.13.5": 1}, "CentOS Linux": {"7.7.1908": 1, "7.2": 1, "7": 858, "8": 4}, "openSUSE Leap": {"15.1": 3, "42.3": 2}, "Red Hat Enterprise Linux Server": {"7.4": 7, "7.6": 15, "7.7": 17, "7.0": 731, "7.5": 8, "7.3": 1}, "OS X": {"10.14.1": 2}, "RedHatEnterpriseServer": {"6.10": 1, "6.8": 1}, "Oracle Linux Server": {"6.10": 1, "7.7": 1}, "Kali GNU/Linux": {"2019.4": 1, "2019.3": 2}, "Amazon Linux": {"2": 209}, "Alpine Linux": {"3.7.1": 34, "3.6.2": 3, "3.11_alpha20190809": 56, "3.7.0": 31, "3.9.2": 83, "3.10.2": 114, "3.7.3": 8, "3.10.1": 22, "3.6.3": 9, "3.9.0": 8, "3.6.5": 3, "3.9.4": 29, "3.9.3": 15, "3.11_alpha20190925": 1, "3.4.6": 3, "3.8.2": 9, "3.8.4": 27}, "SLES": {"12.1": 3, "12.3": 3, "12.2": 3, "12.4": 3}, "Arch Linux": {"2019.1.20": 1, "null": 14, "rolling": 12}, "LinuxMint": {"18.2": 1}, "KDE neon": {"18.04": 1}, "Linux Mint": {"19": 2, "19.1": 12, "19.2": 11, "18.3": 2}, "Amazon Linux AMI": {"2016.03": 1, "2017.09": 2, "2018.03": 462, "2017.03": 4}, "Manjaro Linux": {"18.0.4": 4, "18.1.0": 15, "null": 1}, "Fedora": {"27": 1, "31": 1, "30": 12, "28": 92, "29": 3}, "openSUSE Tumbleweed": {"20190809": 1}, "null": {"null": 2554}, "Red Hat Enterprise Linux": {"8.0": 10}, "Scientific Linux": {"7.6": 1}, "Ubuntu": {"16.04": 3958, "19.10": 1, "17.10": 2, "14.04": 694, "19.04": 71, "18.10": 52, "15.04": 1, "18.04": 1934}, "CentOS": {"6.6": 2, "6.8": 1, "6.4": 1, "6.10": 69, "6.9": 1}, "Deepin": {"15.11": 3}, "debian": {"stretch/sid": 13, "jessie/sid": 22}, "Parrot GNU/Linux": {"4.7": 2}, "EulerOS": {"2.0": 1}, "SUSE LINUX": {"11": 1}, "Alibaba Group Enterprise Linux Server": {"7.2": 1}, "Antergos Linux": {"null": 2}, "Neptune": {"6.0": 1}, "Astra Linux (Orel)": {"2.12.17": 4}, "elementary OS": {"5.0": 1}, "Pop!_OS": {"19.04": 1}, "void": {"rolling": 2}, "Raspbian GNU/Linux": {"10": 1}}, "by_country": {"null": 628, "JP": 351, "DK": 5, "TW": 34, "RS": 3, "AT": 18, "VN": 13, "UY": 5, "IS": 1, "LC": 1, "RW": 3, "MX": 10, "EG": 1, "LB": 1, "CL": 1, "IL": 10, "SE": 35, "HU": 3, "AP": 43, "UA": 20, "BR": 37, "TR": 16, "TH": 12, "SG": 22, "RO": 3, "SA": 1, "IE": 463, "NL": 139, "PL": 31, "CA": 114, "PK": 6, "ZW": 1, "GB": 244, "IT": 13, "CZ": 12, "CH": 44, "NZ": 10, "AR": 8, "LT": 5, "BW": 1, "MD": 3, "DE": 337, "MA": 5, "PT": 15, "MM": 1, "KE": 2, "NG": 3, "ID": 70, "IN": 73, "FI": 26, "EE": 2, "SI": 1, "GT": 1, "US": 16946, "AU": 64, "CI": 1, "BD": 2, "KZ": 1, "SK": 2, "UZ": 1, "FR": 412, "ES": 52, "BH": 1, "GR": 1, "HR": 3, "BY": 1, "UG": 1, "BG": 3, "MK": 1, "PE": 2, "RU": 115, "CN": 181, "BE": 5, "EU": 64, "MY": 2, "NO": 5, "JO": 2, "CO": 10, "HK": 59, "KR": 193, "BO": 1, "PH": 3, "AL": 1, "IQ": 1, "DZ": 2}, "cache_metadata": {"project": "yapf", "date": "20190925", "updated": 1578051008.1863797, "version": "0.2.1", "data_ts": 1569455999}}