{"by_version": {"0.19.0": 50, "0.23.0": 49, "0.2.5": 6, "0.14.0": 130, "0.16.2": 14, "0.25.0": 242, "0.15.2": 7, "0.4.0": 6, "0.2.8": 6, "0.9.0": 6, "0.8.1": 6, "0.1.8": 6, "0.2.3": 6, "0.20.0": 174, "0.12.1": 6, "0.6.3": 6, "0.6.1": 6, "0.2.1": 6, "0.6.0": 6, "0.5.0": 6, "0.27.0": 3181, "0.13.2": 35, "0.26.0": 574, "0.15.1": 7, "0.1.7": 6, "0.12.0": 6, "0.15.0": 6, "0.10.0": 23, "0.20.2": 57, "0.24.0": 136, "0.20.1": 30, "0.16.3": 62, "0.1.9": 6, "0.13.0": 6, "0.3.0": 6, "0.2.6": 6, "0.7.1": 272, "0.11.0": 7, "0.2.9": 6, "0.1.4": 3, "0.2.2": 6, "0.2.0": 6, "0.22.0": 4114, "0.16.1": 9, "0.11.1": 9, "0.8.2": 6, "0.17.0": 276, "0.18.0": 7, "0.16.0": 14, "0.2.7": 6, "0.7.0": 6, "0.12.2": 6, "0.1.6": 3, "0.6.2": 610, "0.21.0": 377, "0.2.4": 6, "0.13.1": 6, "0.3.1": 6, "0.8.0": 6, "0.1.5": 3}, "by_file_type": {"bdist_wheel": 9833, "sdist": 828}, "by_installer": {"setuptools": {"39.0.1": 1, "40.8.0": 1, "41.0.1": 18, "40.4.3": 604, "18.5": 1, "40.6.3": 2}, "pip": {"7.1.0": 1, "8.1.2": 20, "19.1": 821, "9.0.1": 634, "9.0.3": 895, "9.0.0": 15, "7.1.2": 1, "19.1.1": 4912, "8.1.1": 84, "18.1": 1348, "19.0.1": 8, "1.5.4": 1, "18.0": 337, "19.0.2": 6, "10.0.1": 348, "19.0.3": 224, "9.0.2": 4, "1.5.6": 1}, "Browser": {"null": 241}, "requests": {"2.21.0": 2, "2.22.0": 4}, "null": {"null": 1}, "bandersnatch": {"2.2.1": 117, "2.0.0": 4}, "Nexus": {"3.6.0-02": 2, "3.13.0-01": 1, "3.16.1-02": 1, "3.7.1-02": 1}}, "by_implementation": {"CPython": {"3.7.3": 1389, "3.5.4": 43, "3.3.6": 2, "3.5.1+": 12, "3.6.3": 177, "3.7.2": 182, "2.7.15": 16, "3.7.0a4+": 6, "3.6.2": 6, "3.8.0b1+": 7, "3.7.3+": 6, "2.7.16": 1226, "2.7.10": 13, "2.7.14": 31, "2.7.15rc1": 131, "2.7.5": 28, "3.6.5+": 3, "3.8.0a4": 1, "3.5.6": 54, "3.4.9": 2, "3.6.4": 276, "2.7.13": 257, "2.7.6": 24, "3.4.0": 1, "2.7.15+": 1, "3.6.6": 488, "3.5.2": 78, "3.6.7": 1401, "3.5.0": 13, "3.5.2+": 1, "3.4.8": 1, "3.5.7": 877, "3.6.8": 2007, "3.6.5": 119, "3.7.1": 80, "2.7.12": 135, "3.4.3": 6, "3.7.0": 441, "3.4.6": 15, "3.6.1": 5, "2.7.9": 1, "3.5.3": 29, "3.6.8+": 16, "3.4.10": 15, "3.6.0": 17, "3.5.7+": 6, "3.5.5+": 1}, "null": {"null": 1001}, "PyPy": {"5.10.1": 2, "7.2.0.alpha.0": 6, "7.1.0.alpha.0": 2, "7.1.1.beta.0": 4}}, "by_system": {"Linux": 8540, "null": 1001, "Windows": 894, "FreeBSD": 1, "Darwin": 225}, "by_distro": {"null": {"null": 1898}, "openSUSE Tumbleweed": {"20190529": 2, "20190606": 1}, "Red Hat Enterprise Linux": {"8.0": 1}, "openSUSE Leap": {"15.0": 2, "15.1": 1}, "macOS": {"10.13.1": 1, "10.14.4": 26, "10.14": 7, "10.12.6": 4, "10.14.3": 8, "10.12.2": 1, "10.14.6": 2, "10.14.5": 81, "10.13.6": 85, "10.14.1": 3, "10.14.2": 1, "10.13.3": 5, "10.13.4": 1}, "Red Hat Enterprise Linux Server": {"7.6": 116, "7.4": 1, "7.0": 99, "7.5": 2}, "Pop!_OS": {"18.10": 1, "19.04": 2}, "Kali GNU/Linux": {"2019.2": 7, "2019.1": 1}, "Amazon Linux": {"2": 57}, "Fedora": {"29": 5, "30": 6, "28": 59}, "Linux Mint": {"18.3": 2, "18.1": 1, "18.2": 2, "19.1": 11}, "Debian GNU/Linux": {"8": 83, "rodete": 1, "9": 4185, "10": 3}, "Alpine Linux": {"3.7.0": 14, "3.9.4": 15, "3.8.2": 8, "3.4.6": 1, "3.9.2": 9, "3.9.3": 1, "3.9.0": 10}, "Arch Linux": {"null": 12, "rolling": 2}, "Manjaro Linux": {"18.0.4": 14}, "Parrot GNU/Linux": {"4.7": 3, "4.6": 1}, "Raspbian GNU/Linux": {"8": 50, "9": 11}, "Ubuntu": {"18.04": 1455, "14.04": 490, "15.10": 1, "19.04": 14, "17.10": 1, "16.04": 440, "18.10": 11}, "Freedesktop.org": {"18.08.32": 1}, "CentOS Linux": {"7.6.1810": 1, "7": 316}, "CentOS": {"6.9": 1, "6.10": 1}, "elementary OS": {"5.0": 1}, "Zorin OS": {"15": 1, "12": 2}, "Slackware ": {"14.1": 1}, "Anarchy Linux": {"null": 2}, "KDE neon": {"18.04": 1}, "debian": {"jessie/sid": 6}, "Oracle Linux Server": {"7.3": 2}, "Solus": {"4.0": 1}, "Amazon Linux AMI": {"2017.09": 5, "2016.03": 1, "2018.03": 978}, "Scientific Linux": {"7.3": 1}, "RedHatEnterpriseServer": {"6.8": 1}, "Arch Linux ARM": {"null": 1}}, "by_country": {"CN": 239, "DE": 122, "VN": 2, "AU": 16, "PT": 14, "NG": 1, "null": 1453, "IN": 42, "JP": 50, "SG": 10, "RO": 1, "TR": 2, "EE": 1, "PA": 1, "AP": 2, "CA": 268, "JO": 1, "GR": 3, "CO": 1, "BO": 1, "FR": 6, "GB": 25, "HK": 19, "IT": 10, "PL": 10, "IE": 18, "CH": 5, "ES": 5, "MN": 3, "A1": 2, "AL": 2, "PE": 2, "FI": 5, "IL": 7, "BR": 31, "ID": 6, "HU": 2, "UA": 2, "TW": 8, "SE": 6, "DK": 1, "EG": 1, "KY": 1, "CR": 1, "BE": 56, "RU": 21, "KE": 4, "RS": 1, "KR": 10, "NL": 36, "MD": 1, "NO": 2, "AR": 1, "HR": 1, "BG": 4, "PK": 1, "NZ": 1, "US": 8092, "IR": 7, "ZA": 6, "MX": 8, "AT": 1}, "cache_metadata": {"project": "yapf", "date": "20190608", "updated": 1578057361.7158492, "version": "0.2.1", "data_ts": 1560038399}}